pybpod_rotaryencoder_module/__init__.py
pybpod_rotaryencoder_module/module.py
pybpod_rotaryencoder_module/module_api.py
pybpod_rotaryencoder_module/module_gui.py
pybpod_rotaryencoder_module/settings.py
pybpod_rotaryencoder_module/models/__init__.py
pybpod_rotaryencoder_module/models/projects/__init__.py
pybpod_rotaryencoder_module/models/projects/projects_rotaryencoder.py
pybpod_rotaryencoder_module/resources/rotary.png
pybpod_gui_plugin_rotaryencoder-0.1.4.dist-info/LICENSE
pybpod_gui_plugin_rotaryencoder-0.1.4.dist-info/METADATA
pybpod_gui_plugin_rotaryencoder-0.1.4.dist-info/WHEEL
pybpod_gui_plugin_rotaryencoder-0.1.4.dist-info/top_level.txt
pybpod_gui_plugin_rotaryencoder-0.1.4.dist-info/RECORD
